finalcif/__init__.py
finalcif/app_path.py
finalcif/appwindow.py
finalcif/finalcif_start.py
finalcif/cif/__init__.py
finalcif/cif/all_cif_dicts.py
finalcif/cif/atoms.py
finalcif/cif/cif_dict_foo.py
finalcif/cif/cif_file_io.py
finalcif/cif/cif_order.py
finalcif/cif/core_dict.py
finalcif/cif/hkl.py
finalcif/cif/modulation_dict.py
finalcif/cif/powder_dict.py
finalcif/cif/reference.py
finalcif/cif/restraints_dict.py
finalcif/cif/text.py
finalcif/cif/twin_dict.py
finalcif/cif/checkcif/__init__.py
finalcif/cif/checkcif/checkcif.py
finalcif/cif/cod/__init__.py
finalcif/cif/cod/deposit.py
finalcif/cif/cod/deposit_check.py
finalcif/cif/cod/deposition_list.py
finalcif/cif/cod/doi.py
finalcif/cif/cod/upload.py
finalcif/cif/cod/website_parser.py
finalcif/ciforder/__init__.py
finalcif/ciforder/order.py
finalcif/ciforder/order_ui.py
finalcif/ciforder/order_ui.ui
finalcif/datafiles/__init__.py
finalcif/datafiles/bruker_data.py
finalcif/datafiles/bruker_frame.py
finalcif/datafiles/ccdc_mail.py
finalcif/datafiles/data.py
finalcif/datafiles/p4p_reader.py
finalcif/datafiles/sadabs.py
finalcif/datafiles/saint.py
finalcif/datafiles/shelx_lst.py
finalcif/datafiles/utils.py
finalcif/displaymol/__init__.py
finalcif/displaymol/molecule2D.py
finalcif/displaymol/sdm.py
finalcif/displaymol/vtk_molecule.py
finalcif/equip_property/__init__.py
finalcif/equip_property/author_loop_templates.py
finalcif/equip_property/equipment.py
finalcif/equip_property/properties.py
finalcif/equip_property/tools.py
finalcif/gui/__init__.py
finalcif/gui/block_combobox.py
finalcif/gui/combobox.py
finalcif/gui/custom_classes.py
finalcif/gui/dialogs.py
finalcif/gui/edit_button.py
finalcif/gui/equipmenttable.py
finalcif/gui/file_editor.py
finalcif/gui/finalcif_gui_ui.py
finalcif/gui/finalcif_gui_ui.ui
finalcif/gui/import_selector.py
finalcif/gui/import_selector_ui.py
finalcif/gui/import_selector_ui.ui
finalcif/gui/loop_creator.py
finalcif/gui/loop_creator_ui.py
finalcif/gui/loop_creator_ui.ui
finalcif/gui/loops.py
finalcif-156.dist-info/METADATA
finalcif-156.dist-info/WHEEL
finalcif-156.dist-info/entry_points.txt
finalcif-156.dist-info/licenses/LICENSE
finalcif-156.dist-info/RECORD
