Metadata-Version: 2.4
Name: finalcif
Version: 156
Summary: CIF file editor
Project-URL: Homepage, https://dkratzert.de/finalcif.html
Project-URL: Bug Tracker, https://github.com/dkratzert/FinalCif/issues
Author-email: Daniel Kratzert <dkratzert@gmx.de>
License-File: LICENSE
Classifier: Development Status :: 5 - Production/Stable
Classifier: License :: OSI Approved :: MIT License
Classifier: Operating System :: OS Independent
Classifier: Programming Language :: Python :: 3
Classifier: Topic :: Scientific/Engineering :: Chemistry
Requires-Python: >=3.10
Requires-Dist: certifi
Requires-Dist: chardet
Requires-Dist: charset-normalizer
Requires-Dist: crossrefapi
Requires-Dist: docxtpl
Requires-Dist: gemmi
Requires-Dist: hatchling
Requires-Dist: html2text
Requires-Dist: lxml
Requires-Dist: numpy
Requires-Dist: packaging
Requires-Dist: pefile
Requires-Dist: pybind11
Requires-Dist: pyenchant
Requires-Dist: pyside6
Requires-Dist: pyside6-addons
Requires-Dist: python-docx
Requires-Dist: qtawesome
Requires-Dist: qtpy
Requires-Dist: requests
Requires-Dist: shelxfile
Requires-Dist: urllib3
Requires-Dist: wheel
